iisignature.cp39-win32.pyd
iisignature_data/__init__.py
iisignature_data/bchLyndon20.dat
iisignature-0.24.dist-info/License.txt
iisignature-0.24.dist-info/METADATA
iisignature-0.24.dist-info/WHEEL
iisignature-0.24.dist-info/top_level.txt
iisignature-0.24.dist-info/RECORD
