Metadata-Version: 2.1
Name: iisignature
Version: 0.24
Summary: Iterated integral signature calculations
Home-page: https://github.com/bottler/iisignature
Author: Jeremy Reizenstein
Author-email: j.f.reizenstein@warwick.ac.uk
License: MIT
Keywords: signature,logsignature
Platform: UNKNOWN
Classifier: Development Status :: 4 - Beta
Classifier: Intended Audience :: Developers
Classifier: Intended Audience :: Science/Research
Classifier: Intended Audience :: Financial and Insurance Industry
Classifier: Topic :: Scientific/Engineering :: Artificial Intelligence
Classifier: Topic :: Scientific/Engineering :: Mathematics
Classifier: License :: OSI Approved :: MIT License
Classifier: Programming Language :: Python :: 2
Classifier: Programming Language :: Python :: 3
Requires-Dist: numpy (>1.7)
